sphinx_indexed_definitions/__init__.py
sphinx_indexed_definitions/_version.py
sphinx_indexed_definitions-1.1.0.dist-info/METADATA
sphinx_indexed_definitions-1.1.0.dist-info/WHEEL
sphinx_indexed_definitions-1.1.0.dist-info/licenses/LICENSE
sphinx_indexed_definitions-1.1.0.dist-info/RECORD
