Metadata-Version: 2.4
Name: sphinx-indexed-definitions
Version: 1.1.0
Summary: A Sphinx extension that fills the index based on definitions in a Sphinx book
Author-email: Dennis den Ouden-van der Horst <d.denouden-vanderhorst@tudelft.nl>
License: MIT License
License-File: LICENSE
Requires-Python: >=3.10
Requires-Dist: sphinx
Requires-Dist: sphinx-proof
